{"nodes": [{"id": "c_repository_bro974_mtgarchitect_back_scripts_check_endpointcontracts_ps1", "label": "Check-EndpointContracts.ps1", "file_type": "code", "source_file": "C:\\Repository\\bro974\\MTGArchitect\\back\\scripts\\Check-EndpointContracts.ps1", "source_location": "L1"}, {"id": "scripts_check_endpointcontracts_normalize_endpointpath", "label": "Normalize-EndpointPath()", "file_type": "code", "source_file": "C:\\Repository\\bro974\\MTGArchitect\\back\\scripts\\Check-EndpointContracts.ps1", "source_location": "L8"}, {"id": "scripts_check_endpointcontracts_get_sourceendpoints", "label": "Get-SourceEndpoints()", "file_type": "code", "source_file": "C:\\Repository\\bro974\\MTGArchitect\\back\\scripts\\Check-EndpointContracts.ps1", "source_location": "L25"}, {"id": "scripts_check_endpointcontracts_get_documentedendpoints", "label": "Get-DocumentedEndpoints()", "file_type": "code", "source_file": "C:\\Repository\\bro974\\MTGArchitect\\back\\scripts\\Check-EndpointContracts.ps1", "source_location": "L64"}], "edges": [{"source": "c_repository_bro974_mtgarchitect_back_scripts_check_endpointcontracts_ps1", "target": "scripts_check_endpointcontracts_normalize_endpointpath", "relation": "contains", "confidence": "EXTRACTED", "source_file": "C:\\Repository\\bro974\\MTGArchitect\\back\\scripts\\Check-EndpointContracts.ps1", "source_location": "L8", "weight": 1.0}, {"source": "c_repository_bro974_mtgarchitect_back_scripts_check_endpointcontracts_ps1", "target": "scripts_check_endpointcontracts_get_sourceendpoints", "relation": "contains", "confidence": "EXTRACTED", "source_file": "C:\\Repository\\bro974\\MTGArchitect\\back\\scripts\\Check-EndpointContracts.ps1", "source_location": "L25", "weight": 1.0}, {"source": "c_repository_bro974_mtgarchitect_back_scripts_check_endpointcontracts_ps1", "target": "scripts_check_endpointcontracts_get_documentedendpoints", "relation": "contains", "confidence": "EXTRACTED", "source_file": "C:\\Repository\\bro974\\MTGArchitect\\back\\scripts\\Check-EndpointContracts.ps1", "source_location": "L64", "weight": 1.0}, {"source": "scripts_check_endpointcontracts_get_sourceendpoints", "target": "scripts_check_endpointcontracts_normalize_endpointpath", "relation": "calls", "confidence": "EXTRACTED", "source_file": "C:\\Repository\\bro974\\MTGArchitect\\back\\scripts\\Check-EndpointContracts.ps1", "source_location": "L57", "weight": 1.0}, {"source": "scripts_check_endpointcontracts_get_documentedendpoints", "target": "scripts_check_endpointcontracts_normalize_endpointpath", "relation": "calls", "confidence": "EXTRACTED", "source_file": "C:\\Repository\\bro974\\MTGArchitect\\back\\scripts\\Check-EndpointContracts.ps1", "source_location": "L74", "weight": 1.0}], "raw_calls": [{"caller_nid": "scripts_check_endpointcontracts_get_sourceendpoints", "callee": "Get-Content", "is_member_call": false, "source_file": "C:\\Repository\\bro974\\MTGArchitect\\back\\scripts\\Check-EndpointContracts.ps1", "source_location": "L32"}, {"caller_nid": "scripts_check_endpointcontracts_get_sourceendpoints", "callee": "New-Object", "is_member_call": false, "source_file": "C:\\Repository\\bro974\\MTGArchitect\\back\\scripts\\Check-EndpointContracts.ps1", "source_location": "L35"}, {"caller_nid": "scripts_check_endpointcontracts_get_documentedendpoints", "callee": "Get-Content", "is_member_call": false, "source_file": "C:\\Repository\\bro974\\MTGArchitect\\back\\scripts\\Check-EndpointContracts.ps1", "source_location": "L67"}, {"caller_nid": "scripts_check_endpointcontracts_get_documentedendpoints", "callee": "New-Object", "is_member_call": false, "source_file": "C:\\Repository\\bro974\\MTGArchitect\\back\\scripts\\Check-EndpointContracts.ps1", "source_location": "L70"}]}